gshconverter/__init__.py
gshconverter-0.1.0.dist-info/WHEEL
gshconverter-0.1.0.dist-info/METADATA
gshconverter-0.1.0.dist-info/RECORD
