Metadata-Version: 2.1
Name: gshconverter
Version: 0.1.0
Summary: convert between gregorian and solar hijri calendars
Author-email: 5j9 <5j9@users.noreply.github.com>
Requires-Python: >=3.12
Project-URL: Homepage, https://github.com/5j9/gshconverter
